package org.codehaus.janino;

final class Opcode {
   public static final int AALOAD = 50;
   public static final int AASTORE = 83;
   public static final int ACONST_NULL = 1;
   public static final int ALOAD = 25;
   public static final int ALOAD_0 = 42;
   public static final int ALOAD_1 = 43;
   public static final int ALOAD_2 = 44;
   public static final int ALOAD_3 = 45;
   public static final int ANEWARRAY = 189;
   public static final int ARETURN = 176;
   public static final int ARRAYLENGTH = 190;
   public static final int ASTORE = 58;
   public static final int ASTORE_0 = 75;
   public static final int ASTORE_1 = 76;
   public static final int ASTORE_2 = 77;
   public static final int ASTORE_3 = 78;
   public static final int ATHROW = 191;
   public static final int BALOAD = 51;
   public static final int BASTORE = 84;
   public static final int BIPUSH = 16;
   public static final int CALOAD = 52;
   public static final int CASTORE = 85;
   public static final int CHECKCAST = 192;
   public static final int D2F = 144;
   public static final int D2I = 142;
   public static final int D2L = 143;
   public static final int DADD = 99;
   public static final int DALOAD = 49;
   public static final int DASTORE = 82;
   public static final int DCMPG = 152;
   public static final int DCMPL = 151;
   public static final int DCONST_0 = 14;
   public static final int DCONST_1 = 15;
   public static final int DDIV = 111;
   public static final int DLOAD = 24;
   public static final int DLOAD_0 = 38;
   public static final int DLOAD_1 = 39;
   public static final int DLOAD_2 = 40;
   public static final int DLOAD_3 = 41;
   public static final int DMUL = 107;
   public static final int DNEG = 119;
   public static final int DREM = 115;
   public static final int DRETURN = 175;
   public static final int DSTORE = 57;
   public static final int DSTORE_0 = 71;
   public static final int DSTORE_1 = 72;
   public static final int DSTORE_2 = 73;
   public static final int DSTORE_3 = 74;
   public static final int DSUB = 103;
   public static final int DUP = 89;
   public static final int DUP_X1 = 90;
   public static final int DUP_X2 = 91;
   public static final int DUP2 = 92;
   public static final int DUP2_X1 = 93;
   public static final int DUP2_X2 = 94;
   public static final int F2D = 141;
   public static final int F2I = 139;
   public static final int F2L = 140;
   public static final int FADD = 98;
   public static final int FALOAD = 48;
   public static final int FASTORE = 81;
   public static final int FCMPG = 150;
   public static final int FCMPL = 149;
   public static final int FCONST_0 = 11;
   public static final int FCONST_1 = 12;
   public static final int FCONST_2 = 13;
   public static final int FDIV = 110;
   public static final int FLOAD = 23;
   public static final int FLOAD_0 = 34;
   public static final int FLOAD_1 = 35;
   public static final int FLOAD_2 = 36;
   public static final int FLOAD_3 = 37;
   public static final int FMUL = 106;
   public static final int FNEG = 118;
   public static final int FREM = 114;
   public static final int FRETURN = 174;
   public static final int FSTORE = 56;
   public static final int FSTORE_0 = 67;
   public static final int FSTORE_1 = 68;
   public static final int FSTORE_2 = 69;
   public static final int FSTORE_3 = 70;
   public static final int FSUB = 102;
   public static final int GETFIELD = 180;
   public static final int GETSTATIC = 178;
   public static final int GOTO = 167;
   public static final int GOTO_W = 200;
   public static final int I2B = 145;
   public static final int I2C = 146;
   public static final int I2D = 135;
   public static final int I2F = 134;
   public static final int I2L = 133;
   public static final int I2S = 147;
   public static final int IADD = 96;
   public static final int IALOAD = 46;
   public static final int IAND = 126;
   public static final int IASTORE = 79;
   public static final int ICONST_M1 = 2;
   public static final int ICONST_0 = 3;
   public static final int ICONST_1 = 4;
   public static final int ICONST_2 = 5;
   public static final int ICONST_3 = 6;
   public static final int ICONST_4 = 7;
   public static final int ICONST_5 = 8;
   public static final int IDIV = 108;
   public static final int IF_ACMPEQ = 165;
   public static final int IF_ACMPNE = 166;
   public static final int IF_ICMPEQ = 159;
   public static final int IF_ICMPNE = 160;
   public static final int IF_ICMPLT = 161;
   public static final int IF_ICMPGE = 162;
   public static final int IF_ICMPGT = 163;
   public static final int IF_ICMPLE = 164;
   public static final int IFEQ = 153;
   public static final int IFNE = 154;
   public static final int IFLT = 155;
   public static final int IFGE = 156;
   public static final int IFGT = 157;
   public static final int IFLE = 158;
   public static final int IFNONNULL = 199;
   public static final int IFNULL = 198;
   public static final int IINC = 132;
   public static final int ILOAD = 21;
   public static final int ILOAD_0 = 26;
   public static final int ILOAD_1 = 27;
   public static final int ILOAD_2 = 28;
   public static final int ILOAD_3 = 29;
   public static final int IMUL = 104;
   public static final int INEG = 116;
   public static final int INSTANCEOF = 193;
   public static final int INVOKEDYNAMIC = 186;
   public static final int INVOKEINTERFACE = 185;
   public static final int INVOKESPECIAL = 183;
   public static final int INVOKESTATIC = 184;
   public static final int INVOKEVIRTUAL = 182;
   public static final int IOR = 128;
   public static final int IREM = 112;
   public static final int IRETURN = 172;
   public static final int ISHL = 120;
   public static final int ISHR = 122;
   public static final int ISTORE = 54;
   public static final int ISTORE_0 = 59;
   public static final int ISTORE_1 = 60;
   public static final int ISTORE_2 = 61;
   public static final int ISTORE_3 = 62;
   public static final int ISUB = 100;
   public static final int IUSHR = 124;
   public static final int IXOR = 130;
   /** @deprecated */
   @Deprecated
   public static final int JSR = 168;
   public static final int JSR_W = 201;
   public static final int L2D = 138;
   public static final int L2F = 137;
   public static final int L2I = 136;
   public static final int LADD = 97;
   public static final int LALOAD = 47;
   public static final int LAND = 127;
   public static final int LASTORE = 80;
   public static final int LCMP = 148;
   public static final int LCONST_0 = 9;
   public static final int LCONST_1 = 10;
   public static final int LDC = 18;
   public static final int LDC_W = 19;
   public static final int LDC2_W = 20;
   public static final int LDIV = 109;
   public static final int LLOAD = 22;
   public static final int LLOAD_0 = 30;
   public static final int LLOAD_1 = 31;
   public static final int LLOAD_2 = 32;
   public static final int LLOAD_3 = 33;
   public static final int LMUL = 105;
   public static final int LNEG = 117;
   public static final int LOOKUPSWITCH = 171;
   public static final int LOR = 129;
   public static final int LREM = 113;
   public static final int LRETURN = 173;
   public static final int LSHL = 121;
   public static final int LSHR = 123;
   public static final int LSTORE = 55;
   public static final int LSTORE_0 = 63;
   public static final int LSTORE_1 = 64;
   public static final int LSTORE_2 = 65;
   public static final int LSTORE_3 = 66;
   public static final int LSUB = 101;
   public static final int LUSHR = 125;
   public static final int LXOR = 131;
   public static final int MONITORENTER = 194;
   public static final int MONITOREXIT = 195;
   public static final int MULTIANEWARRAY = 197;
   public static final int NEW = 187;
   public static final int NEWARRAY = 188;
   public static final int NOP = 0;
   public static final int POP = 87;
   public static final int POP2 = 88;
   public static final int PUTFIELD = 181;
   public static final int PUTSTATIC = 179;
   /** @deprecated */
   @Deprecated
   public static final int RET = 169;
   public static final int RETURN = 177;
   public static final int SALOAD = 53;
   public static final int SASTORE = 86;
   public static final int SIPUSH = 17;
   public static final int SWAP = 95;
   public static final int TABLESWITCH = 170;
   public static final int WIDE = 196;
   public static final short INVALID_OPCODE = -1;
   public static final short SD_MASK = 31;
   public static final short SD_M4 = 0;
   public static final short SD_M3 = 1;
   public static final short SD_M2 = 2;
   public static final short SD_M1 = 3;
   public static final short SD_P0 = 4;
   public static final short SD_P1 = 5;
   public static final short SD_P2 = 6;
   public static final short SD_0 = 7;
   public static final short SD_GETFIELD = 9;
   public static final short SD_GETSTATIC = 10;
   public static final short SD_PUTFIELD = 11;
   public static final short SD_PUTSTATIC = 12;
   public static final short SD_INVOKEVIRTUAL = 13;
   public static final short SD_INVOKESPECIAL = 14;
   public static final short SD_INVOKESTATIC = 15;
   public static final short SD_INVOKEINTERFACE = 16;
   public static final short SD_MULTIANEWARRAY = 18;
   public static final short OP1_MASK = 480;
   public static final short OP1_SB = 32;
   public static final short OP1_UB = 64;
   public static final short OP1_SS = 96;
   public static final short OP1_CP1 = 128;
   public static final short OP1_CP2 = 160;
   public static final short OP1_LV1 = 192;
   public static final short OP1_LV2 = 224;
   public static final short OP1_BO2 = 256;
   public static final short OP1_BO4 = 288;
   public static final short OP1_LOOKUPSWITCH = 320;
   public static final short OP1_TABLESWITCH = 352;
   public static final short OP1_JSR = 384;
   public static final short OP2_MASK = 1536;
   public static final short OP2_SB = 512;
   public static final short OP2_SS = 1024;
   public static final short OP3_MASK = 2048;
   public static final short OP3_SB = 2048;
   public static final short IO_MASK = 28672;
   public static final short IO_LV_0 = 4096;
   public static final short IO_LV_1 = 8192;
   public static final short IO_LV_2 = 12288;
   public static final short IO_LV_3 = 16384;
   public static final short NO_FALLTHROUGH = Short.MIN_VALUE;
   public static final short[] OPCODE_PROPERTIES = new short[]{4, 5, 5, 5, 5, 5, 5, 5, 5, 6, 6, 5, 5, 5, 6, 6, 37, 101, 133, 165, 166, 197, 198, 197, 198, 197, 4101, 8197, 12293, 16389, 4102, 8198, 12294, 16390, 4101, 8197, 12293, 16389, 4102, 8198, 12294, 16390, 4101, 8197, 12293, 16389, 3, 4, 3, 4, 3, 3, 3, 3, 195, 194, 195, 194, 195, 4099, 8195, 12291, 16387, 4098, 8194, 12290, 16386, 4099, 8195, 12291, 16387, 4098, 8194, 12290, 16386, 4099, 8195, 12291, 16387, 1, 0, 1, 0, 1, 1, 1, 1, 3, 2, 5, 5, 5, 6, 6, 6, 4, 3, 2, 3, 2, 3, 2, 3, 2, 3, 2, 3, 2, 3, 2, 3, 2, 3, 2, 3, 2, 4, 4, 4, 4, 3, 3, 3, 3, 3, 3, 3, 2, 3, 2, 3, 2, 708, 5, 4, 5, 3, 3, 4, 4, 5, 5, 3, 4, 3, 4, 4, 4, 1, 3, 3, 1, 1, 259, 259, 259, 259, 259, 259, 258, 258, 258, 258, 258, 258, 258, 258, -32508, 388, -32572, 355, 323, -32761, -32761, -32761, -32761, -32765, -32761, 170, 172, 169, 171, 173, 174, 175, 2736, -1, 165, 68, 164, 4, -32765, 164, 164, 3, 3, -1, 690, 259, 259, -32476, 293, -1, -1, -1, -1, -1, -1, -1, -1, -1, -1, -1, -1, -1, -1, -1, -1, -1, -1, -1, -1, -1, -1, -1, -1, -1, -1, -1, -1, -1, -1, -1, -1, -1, -1, -1, -1, -1, -1, -1, -1, -1, -1, -1, -1, -1, -1, -1, -1, -1, -1, -1, -1, -1, -1};
   public static final short[] WIDE_OPCODE_PROPERTIES = new short[256];

   private Opcode() {
   }

   static {
      for(int i = 0; i < WIDE_OPCODE_PROPERTIES.length; ++i) {
         WIDE_OPCODE_PROPERTIES[i] = -1;
      }

      WIDE_OPCODE_PROPERTIES[21] = 229;
      WIDE_OPCODE_PROPERTIES[23] = 229;
      WIDE_OPCODE_PROPERTIES[25] = 229;
      WIDE_OPCODE_PROPERTIES[22] = 230;
      WIDE_OPCODE_PROPERTIES[24] = 230;
      WIDE_OPCODE_PROPERTIES[54] = 227;
      WIDE_OPCODE_PROPERTIES[56] = 227;
      WIDE_OPCODE_PROPERTIES[58] = 227;
      WIDE_OPCODE_PROPERTIES[55] = 226;
      WIDE_OPCODE_PROPERTIES[57] = 226;
      WIDE_OPCODE_PROPERTIES[132] = 1252;
      WIDE_OPCODE_PROPERTIES[169] = 228;
   }
}
